Mint_NM/__init__.py
Mint_NM/closedrootfinder_module.py
Mint_NM/neuralnet_module.py
Mint_NM/openrootfinder_module.py
mint_nm-0.1.27.dist-info/licenses/LICENSE.txt
mint_nm-0.1.27.dist-info/METADATA
mint_nm-0.1.27.dist-info/WHEEL
mint_nm-0.1.27.dist-info/top_level.txt
mint_nm-0.1.27.dist-info/RECORD
